README.md
setup.py
managealooma/__init__.py
managealooma/column_ddl.py
managealooma/consolidations.py
managealooma/dictionary_difference.py
managealooma/events.py
managealooma/inputs.py
managealooma/mappings.py
managealooma/samples.py
managealooma/secrets.py
managealooma/system.py
managealooma/transformation_functions.py
managealooma/transformation_test.py
managealooma.egg-info/PKG-INFO
managealooma.egg-info/SOURCES.txt
managealooma.egg-info/dependency_links.txt
managealooma.egg-info/not-zip-safe
managealooma.egg-info/requires.txt
managealooma.egg-info/top_level.txt