Metadata-Version: 2.1
Name: managealooma
Version: 0.1.13
Summary: Code to manage the Alooma ETL tool.
Home-page: http://pypi.python.org/pypi/ManageAlooma/
Author: Jay Rosenthal
Author-email: jay.rosenthal@hover.to
License: LICENSE.txt
Platform: UNKNOWN
